eponym/__init__.py
eponym/generator.py
eponym/data/__init__.py
eponym/data/descriptors.py
eponym/data/things.py
eponym-1.0.0.dist-info/LICENSE
eponym-1.0.0.dist-info/METADATA
eponym-1.0.0.dist-info/WHEEL
eponym-1.0.0.dist-info/top_level.txt
eponym-1.0.0.dist-info/RECORD
