Metadata-Version: 2.1
Name: eponym
Version: 1.0.0
Summary: Decent username generator based on handpicked wordlists
Home-page: https://github.com/DoctorJohn/eponym
Author: Jonathan Ehwald
Author-email: pypi@ehwald.info
License: MIT License
Platform: UNKNOWN
Classifier: Intended Audience :: Developers
Classifier: License :: OSI Approved :: MIT License
Classifier: Operating System :: OS Independent
Classifier: Programming Language :: Python
Classifier: Programming Language :: Python :: 3
Classifier: Programming Language :: Python :: 3.3
Classifier: Programming Language :: Python :: 3.4
Classifier: Programming Language :: Python :: 3.5
Classifier: Programming Language :: Python :: 3.6
Classifier: Programming Language :: Python :: 3.7
